<?xml version="1.0" encoding="utf-8"?><?xml-stylesheet href="../REDGLOBAL_GLB_T_LANG_BULK_dash.xsl?v={188CF4A4-7D3C-DE51-E050-040A84062911}" type="text/xsl"?><rows><title>IGRP</title><version>188C713F4E15E9BAE050040A840620B8</version><link>/images/IGRP2.2/xml/IGRP-home.xml</link><site><welcome_note>Ola</welcome_note><footer_note>2011 - Copyright NOSI</footer_note><user_name>red-igrp</user_name><button		type="specific"><title>Sair</title><app>RED</app><page /><link>#</link><target>_self</target><img>exit.png</img></button></site><app>REDGLOBAL</app><page>GLB_T_LANG</page><navigation	file="navigation.xml?v={188CF4A4-7D39-DE51-E050-040A84062911}"	prm_app="p_prm_app"	prm_page="p_prm_page"	prm_action="p_prm_action" /><top_menu	file="/images/IGRP2.2/xml/IGRP-top_menu.xml" /><slide-menu	file="slide-menu.xml?v=7" /><content		type="dash"><title>Linguas</title><menu><item		type="specific"><title>Liguas Aplicacao</title><app>REDGLOBAL</app><page>GLB_T_LANG</page><link>LANG_ENV</link><target>_self</target><img>m_categoria.png</img></item><item		type="specific"><title>Lingua</title><app>REDGLOBAL</app><page>GLB_T_LANG</page><link>BULK</link><target>_self</target><img>conteudos.png</img></item></menu><filter		tab=""><label><code		name="p_code"	type="text"	maxlength="22">Code</code><description		name="p_description"	type="text"	maxlength="150">Description</description><cod_lang		name="p_cod_lang"	type="select"	maxlength="30">Lingua</cod_lang></label><value><code		name="p_code">Pnfvfuqgxjr</code><description		name="p_description">Fmctnebuvobmdhpwklqwksmfwin</description></value><list><cod_lang		name="p_cod_lang"><option><text>-- Lingua --</text><value /></option><option><text>Opcao 1</text><value>1</value></option><option		selected="true"><text>Opcao 2</text><value>2</value></option><option><text>Opcao 3</text><value>3</value></option></cod_lang></list><tools-bar><item		type="specific"><title>Pesquisar</title><app>REDGLOBAL</app><page>GLB_T_LANG</page><link>BULK</link><target>_self</target><img>search.png</img></item></tools-bar></filter><table		operation="menu"><label><code		name="p_code"	type="text"	align="left">Code</code><description		name="p_description"	type="text"	align="left">Description</description><cod_lang		name="p_cod_lang"	type="text"	align="left">Lingua</cod_lang></label><value><row><code		name="p_cod_lang"	type="text"	align="left">Qdwwmwx</code><description		name="p_cod_lang"	type="text"	align="left">Sganbayzp</description><cod_lang		name="p_cod_lang"	type="text"	align="left">Nrrhdmqvvjanekx</cod_lang></row><row><code		name="p_cod_lang"	type="text"	align="left">Yxrctmirgpdp</code><description		name="p_cod_lang"	type="text"	align="left">Ediwcnsthzsgnkbuqbzlsdrl</description><cod_lang		name="p_cod_lang"	type="text"	align="left">Muguxrrueslogxsx</cod_lang></row><row><code		name="p_cod_lang"	type="text"	align="left">Elbdnckqr</code><description		name="p_cod_lang"	type="text"	align="left">Ghzdpcdxljkbeksbrznop</description><cod_lang		name="p_cod_lang"	type="text"	align="left">Wuhfoidmobequkhvjzq</cod_lang></row><row><code		name="p_cod_lang"	type="text"	align="left">Tcxwnscaqzuocnmo</code><description		name="p_cod_lang"	type="text"	align="left">Spszpafllfbbhhgqmajmjgf</description><cod_lang		name="p_cod_lang"	type="text"	align="left">Xarorfgd</cod_lang></row><row><code		name="p_cod_lang"	type="text"	align="left">Niprofndyoak</code><description		name="p_cod_lang"	type="text"	align="left">Hmvypxsttqpjnhfmpitkq</description><cod_lang		name="p_cod_lang"	type="text"	align="left">Vmeqzymunmtszglkyatmwwwxavwxi</cod_lang></row></value><tools-bar><item		type="specific"><title>Novo</title><app>REDGLOBAL</app><page>GLB_T_LANG</page><link>FORM</link><target>_self</target><img>add.png</img></item></tools-bar><context-menu><item		type="specific"><title>Editar</title><app>REDGLOBAL</app><page>GLB_T_LANG</page><link>FORM</link><target>_self</target><img>edit.png</img></item><item		type="specific"><title>Eliminar</title><app>REDGLOBAL</app><page>GLB_T_LANG</page><link>BULK</link><target>confirm</target><img>delete.png</img></item></context-menu></table></content></rows>