<?xml version="1.0" encoding="utf-8"?><?xml-stylesheet href="../REDGLOBAL_TESTE_GERADOR_dash.xsl?v={1CA5920C-4012-432A-E050-040A84065EDB}" type="text/xsl"?><rows><title>IGRP</title><version>201532</version><link>/images/images/IGRP2.2//xml/IGRP-home.xml</link><site><welcome_note>Ola</welcome_note><footer_note>2011 - Copyright NOSI</footer_note><user_name>red-igrp</user_name><button		type="specific"	code=""><title>Sair</title><app>RED</app><page /><link>#</link><target>_self</target><img>exit.png</img></button></site><app>REDGLOBAL</app><page>TESTE</page><plsql><action>GERADOR</action><package_db>REDGLOBAL_TESTE_GERADOR_DB</package_db><package_html>REDGLOBAL_TESTE_GERADOR_HTML</package_html><package_instance /><with_replace>false</with_replace><with_label>false</with_label><with_biztalk>false</with_biztalk><dynamic_menu>false</dynamic_menu><copy_menu>false</copy_menu><package_copy_db /><package_copy_html /></plsql><navigation	file="navigation.xml?v={1CA5920C-4010-432A-E050-040A84065EDB}"	prm_app="p_prm_app"	prm_page="p_prm_page"	prm_action="p_prm_action" /><top_menu	file="/images/images/IGRP2.2//xml/IGRP-top_menu.xml" /><slide-menu	file="slide-menu.xml?v=" /><content		type="dash"><title>TESTE_GERADOR</title><view><label><nome		name="p_nome"	type="text"	required="true"	maxlength="30"	code="NOME">Nome</nome><view_foto		name="p_view_foto"	type="text"	maxlength="2000"	code="">Foto</view_foto></label><value><nome		name="p_nome">Gsbehmlhyqmvdsrvlaatrdhm</nome><view_foto		name="p_view_foto">/images/IGRP/img/Dashboard_1024.jpg</view_foto></value></view><table		operation=""><label></label><value><row></row><row></row><row></row><row></row><row></row></value></table></content></rows>