<?xml version="1.0" encoding="utf-8"?><?xml-stylesheet href="../REDGLOBAL_REDWFGLB_T_ACTIVITY_CLASS_BULK_dash.xsl" type="text/xsl"?><rows><title>IGRP</title><link>/images/IGRP/xml/IGRP-home.xml</link><site><welcome_note>Ola</welcome_note><footer_note>2011 - Copyright NOSI</footer_note><user_name>red-igrp</user_name><button		type="specific"><title>Sair</title><app>RED</app><page /><link>#</link><target>_self</target><img>exit.png</img></button></site><app>REDGLOBAL</app><page>REDWF.GLB_T_ACTIVITY_CLASS</page><navigation	file="navigation.xml?v=14"	prm_app="p_prm_app"	prm_page="p_prm_page"	prm_action="p_prm_action" /><top_menu	file="/images/IGRP/xml/IGRP-top_menu.xml" /><slide-menu	file="slide-menu.xml?v=14" /><content><title>Classificacao Etapa</title><messages><message		type="confirm">Deseja continuar a Accao?</message></messages><filter><label><self_id>Tipo</self_id></label><value></value><list><self_id		name="p_self_id"><option><text>-- Tipo --</text><value /></option><option><text>EVENT</text><value>21</value></option><option><text>EVENT</text><value>202</value></option><option><text>EVENT</text><value>49</value></option><option><text>EVENT</text><value>48</value></option><option><text>EVENT</text><value>47</value></option><option><text>Final(END)</text><value>244</value></option><option><text>Final(END)</text><value>6</value></option><option><text>Final(END)</text><value>185</value></option><option><text>Final(END)</text><value>184</value></option><option><text>Final(END)</text><value>187</value></option><option><text>GATEWAY</text><value>23</value></option><option><text>GATEWAY</text><value>7</value></option><option><text>GATEWAY</text><value>45</value></option><option><text>GATEWAY</text><value>4</value></option><option><text>GATEWAY</text><value>46</value></option><option><text>INTERMEDIATE</text><value>246</value></option><option><text>INTERMEDIATE</text><value>221</value></option><option><text>INTERMEDIATE</text><value>222</value></option><option><text>INTERMEDIATE</text><value>241</value></option><option><text>INTERMEDIATE</text><value>225</value></option><option><text>INTERMEDIATE</text><value>245</value></option><option><text>INTERMEDIATE</text><value>224</value></option><option><text>INTERMEDIATE</text><value>223</value></option><option><text>Inicial(START)</text><value>5</value></option><option><text>Inicial(START)</text><value>243</value></option><option><text>Inicial(START)</text><value>188</value></option><option><text>Inicial(START)</text><value>186</value></option><option><text>Inicial(START)</text><value>182</value></option><option><text>Inicial(START)</text><value>183</value></option><option><text>Inicial(START)</text><value>181</value></option><option><text>TASK</text><value>242</value></option><option><text>TASK</text><value>2</value></option><option><text>TASK</text><value>22</value></option><option><text>TASK</text><value>44</value></option><option><text>TASK</text><value>43</value></option></self_id></list><tools-bar><item		type="specific"><title>Pesquisar</title><app>RED</app><page>REDWF.GLB_T_ACTIVITY_CLASS</page><link>BULK</link><target>_self</target><img>search.png</img></item></tools-bar></filter><form><label><id>id</id><self_id>Tipo</self_id><code>Codigo</code><name>Nome</name><associacoes		type="separatorlist">Associacoes</associacoes><classificacao>Classificacao</classificacao></label><value><code		name="p_code">Uhslgqmjndtvu</code><name		name="p_name">Wnsyrjzvjkeedqoz</name><hidden		name="p_id">4660319</hidden></value><list><self_id		name="p_self_id"><option><text>-- Tipo --</text><value /></option><option><text>CONDITION</text><value>188</value></option><option><text>Decisao(SPLIT)</text><value>7</value></option><option><text>EVENT</text><value>21</value></option><option><text>Final(END)</text><value>6</value></option><option><text>GATEWAY</text><value>23</value></option><option><text>INCLUSIVE</text><value>45</value></option><option><text>INTERMEDIATE</text><value>221</value></option><option><text>Inicial(START)</text><value>5</value></option><option><text>Juncao(JOIN)</text><value>4</value></option><option><text>MESSAGE RECEIVE</text><value>223</value></option><option><text>MESSAGE RECEIVE</text><value>181</value></option><option><text>MESSAGE RECEIVE</text><value>49</value></option><option><text>MESSAGE RECEIVE</text><value>44</value></option><option><text>MESSAGE SEND</text><value>185</value></option><option><text>MESSAGE SEND</text><value>48</value></option><option><text>MESSAGE SEND</text><value>222</value></option><option><text>MESSAGE SEND</text><value>43</value></option><option><text>MULTI RECEIVE</text><value>243</value></option><option><text>MULTI RECEIVE</text><value>245</value></option><option><text>MULTI SEND</text><value>244</value></option><option><text>MULTI SEND</text><value>246</value></option><option><text>Normal(USER)</text><value>2</value></option><option><text>PARALLEL</text><value>46</value></option><option><text>REGULAR</text><value>183</value></option><option><text>REGULAR</text><value>184</value></option><option><text>SCRIPT</text><value>242</value></option><option><text>SIGNAL RECEIVE</text><value>202</value></option><option><text>SIGNAL RECEIVE</text><value>186</value></option><option><text>SIGNAL RECEIVE</text><value>241</value></option><option><text>SIGNAL SEND</text><value>187</value></option><option><text>SIGNAL SEND</text><value>225</value></option><option><text>TASK</text><value>22</value></option><option><text>TIMER</text><value>47</value></option><option><text>TIMER</text><value>224</value></option><option><text>TIMER</text><value>182</value></option></self_id><classificacao		name="p_classificacao"><option><text>-- Classificacao --</text><value /></option><option><text>CONDITION</text><value>188</value></option><option><text>Decisao(SPLIT)</text><value>7</value></option><option><text>EVENT</text><value>21</value></option><option><text>Final(END)</text><value>6</value></option><option><text>GATEWAY</text><value>23</value></option><option><text>INCLUSIVE</text><value>45</value></option><option><text>INTERMEDIATE</text><value>221</value></option><option><text>Inicial(START)</text><value>5</value></option><option><text>Juncao(JOIN)</text><value>4</value></option><option><text>MESSAGE RECEIVE</text><value>223</value></option><option><text>MESSAGE RECEIVE</text><value>181</value></option><option><text>MESSAGE RECEIVE</text><value>49</value></option><option><text>MESSAGE RECEIVE</text><value>44</value></option><option><text>MESSAGE SEND</text><value>185</value></option><option><text>MESSAGE SEND</text><value>48</value></option><option><text>MESSAGE SEND</text><value>222</value></option><option><text>MESSAGE SEND</text><value>43</value></option><option><text>MULTI RECEIVE</text><value>243</value></option><option><text>MULTI RECEIVE</text><value>245</value></option><option><text>MULTI SEND</text><value>244</value></option><option><text>MULTI SEND</text><value>246</value></option><option><text>Normal(USER)</text><value>2</value></option><option><text>PARALLEL</text><value>46</value></option><option><text>REGULAR</text><value>183</value></option><option><text>REGULAR</text><value>184</value></option><option><text>SCRIPT</text><value>242</value></option><option><text>SIGNAL RECEIVE</text><value>202</value></option><option><text>SIGNAL RECEIVE</text><value>186</value></option><option><text>SIGNAL RECEIVE</text><value>241</value></option><option><text>SIGNAL SEND</text><value>187</value></option><option><text>SIGNAL SEND</text><value>225</value></option><option><text>TASK</text><value>22</value></option><option><text>TIMER</text><value>47</value></option><option><text>TIMER</text><value>224</value></option><option><text>TIMER</text><value>182</value></option></classificacao></list><table><associacoes><label><classificacao		name="p_classificacao"	type="select">Classificacao</classificacao><classificacao_desc		name="p_classificacao_desc"	type="select">Classificacao</classificacao_desc><associacoes_id		name="p_associacoes_id"	type="hidden">Classificacao</associacoes_id></label><value></value></associacoes></table><tools-bar><item		type="specific"><title>Gravar</title><app>REDGLOBAL</app><page>REDWF.GLB_T_ACTIVITY_CLASS</page><link>FORM</link><target>submit</target><img>save.png</img></item><item		type="specific"><title>Voltar</title><app>REDGLOBAL</app><page>REDWF.GLB_T_ACTIVITY_CLASS</page><link>BULK</link><target>_self</target><img>back.png</img></item></tools-bar></form><table><label><tipo>Tipo</tipo><code>Codigo</code><name>Nome</name></label><value><row><tipo>Riouqcajmcipa</tipo><code>Fudsqghwevclhsa</code><name>Tghzqsxqqjgywaabopnydjwknuu</name></row><row><tipo>Nqvtpucyixbvdjqngiyslpkkcxe</tipo><code>Acudjtj</code><name>Djwfybw</name></row><row><tipo>Zeljrvdyjefpnaaqwxcsrlbhsn</tipo><code>Fkvkktvuusifkhatx</code><name>Kwzgzypnyzrrepbqoidzzjgigbd</name></row><row><tipo>Vqlvxgzmrvxtjblz</tipo><code>Viwoohzdecrxdeu</code><name>Biwfqevlyjxkpzjfofvpkxyu</name></row><row><tipo>Mvkdhfwfpps</tipo><code>Uuusuzegj</code><name>Simmnbtio</name></row></value><tools-bar><item		type="specific"><title>Novo</title><app>REDGLOBAL</app><page>REDWF.GLB_T_ACTIVITY_CLASS</page><link>FORM</link><target>_self</target><img>add.png</img></item></tools-bar><context-menu><item		type="specific"><title>Editar</title><app>REDGLOBAL</app><page>REDWF.GLB_T_ACTIVITY_CLASS</page><link>FORM</link><target>_self</target><img>edit.png</img></item><item		type="specific"><title>Eliminar</title><app>REDGLOBAL</app><page>REDWF.GLB_T_ACTIVITY_CLASS</page><link>BULK</link><target>confirm</target><img>delete.png</img></item></context-menu></table></content></rows>