<?xml version="1.0" encoding="utf-8"?><?xml-stylesheet href="../REDGLOBAL_CONF_PROCESSO_CONF_ENGINE_form.xsl?v={10DDEDAC-8FAF-A81B-E050-040A840656C3}" type="text/xsl"?><rows><title>IGRP</title><version>201510</version><link>/images/IGRP2.2/xml/IGRP-home.xml</link><site><welcome_note>Ola</welcome_note><footer_note>2011 - Copyright NOSI</footer_note><user_name>red-igrp</user_name><button		type="specific"><title>Sair</title><app /><page /><link>#</link><target>_self</target><img>exit.png</img></button></site><app>REDGLOBAL</app><page>CONF_PROCESSO</page><navigation	file="navigation.xml?v={10DDEDAC-8FAE-A81B-E050-040A840656C3}"	prm_app="p_prm_app"	prm_page="p_prm_page"	prm_action="p_prm_action" /><top_menu	file="/images/IGRP2.2/xml/IGRP-top_menu.xml" /><slide-menu	file="slide-menu.xml?v=21" /><language	file="/images/IGRP2.2/xml/IGRP-language.xml" /><content		type="form"><title>ENGINE PROCESSO 2</title><form		tab=""><label><proc_tp_fk		name="p_proc_tp_fk"	type="selectchange"	required="true"	change="true"	maxlength="30">Processo</proc_tp_fk><acti_tp_fk		name="p_acti_tp_fk"	type="selectchange"	required="true"	change="true"	maxlength="30">Etapa</acti_tp_fk><class_fk		name="p_class_fk"	type="select"	required="true"	maxlength="30">Classificacao</class_fk><start_mode		name="p_start_mode"	type="select"	maxlength="30">Execucao</start_mode><acti_to_from_fk		name="p_acti_to_from_fk"	type="select"	maxlength="30">Etapa Origem</acti_to_from_fk><opcoes		type="separator">Opcoes GATE/MSG_REC</opcoes><condition		name="p_condition"	type="select"	maxlength="30">Condicao</condition><event_occour		name="p_event_occour"	type="select"	maxlength="30">Evento</event_occour><recbido		name="p_recbido"	type="select"	maxlength="30">Recebido/Enviado</recbido><msg_tipo_occour		name="p_msg_tipo_occour"	type="select"	maxlength="30">Codigo/MSG</msg_tipo_occour><destinos		type="list">Destinos</destinos><acti_tp_to_fk		name="p_acti_tp_to_fk"	type="text"	rel="destinos"	maxlength="30">id_tp_etapa</acti_tp_to_fk><etapa		name="p_etapa"	type="text"	rel="destinos"	maxlength="30">Etapa</etapa><conditions		name="p_conditions"	type="text"	rel="destinos"	maxlength="30">Condicao</conditions><events		type="list">Eventos</events><event		name="p_event"	type="text"	rel="events"	maxlength="30">Evento</event><acti_trans_to		name="p_acti_trans_to"	type="text"	rel="events"	maxlength="30">Destino</acti_trans_to><acti_com_to		name="p_acti_com_to"	type="text"	rel="events"	maxlength="30">Comunic</acti_com_to><msg_tipo		name="p_msg_tipo"	type="text"	rel="events"	maxlength="30">Codigo/MSG</msg_tipo></label><value><acti_tp_to_fk		name="p_acti_tp_to_fk">Xwysxrerxpjxrgzvopflrtd</acti_tp_to_fk><etapa		name="p_etapa">Kotrjhohejgvpklkzwxz</etapa><conditions		name="p_conditions">Oqplwpgxptilrkhzsybz</conditions><event		name="p_event">Hqlfnmdlxhuvw</event><acti_trans_to		name="p_acti_trans_to">Jygxippbqcpckmzmqhxzvd</acti_trans_to><acti_com_to		name="p_acti_com_to">Zbeejpewainxbnrbguxtvrnztsuhp</acti_com_to><msg_tipo		name="p_msg_tipo">Ukkclhyulczqmeyda</msg_tipo></value><list><proc_tp_fk		name="p_proc_tp_fk"><option><text>-- Processo --</text><value /></option><option		selected="true"><text>Opcao 1</text><value>1</value></option><option><text>Opcao 2</text><value>2</value></option><option><text>Opcao 3</text><value>3</value></option></proc_tp_fk><acti_tp_fk		name="p_acti_tp_fk"><option><text>-- Etapa --</text><value /></option><option><text>Opcao 1</text><value>1</value></option><option		selected="true"><text>Opcao 2</text><value>2</value></option><option><text>Opcao 3</text><value>3</value></option></acti_tp_fk><class_fk		name="p_class_fk"><option><text>-- Classificacao --</text><value /></option><option><text>Opcao 1</text><value>1</value></option><option		selected="true"><text>Opcao 2</text><value>2</value></option><option><text>Opcao 3</text><value>3</value></option></class_fk><start_mode		name="p_start_mode"><option><text>-- Execucao --</text><value /></option><option><text>Opcao 1</text><value>1</value></option><option		selected="true"><text>Opcao 2</text><value>2</value></option><option><text>Opcao 3</text><value>3</value></option></start_mode><acti_to_from_fk		name="p_acti_to_from_fk"><option><text>-- Etapa Origem --</text><value /></option><option><text>Opcao 1</text><value>1</value></option><option		selected="true"><text>Opcao 2</text><value>2</value></option><option><text>Opcao 3</text><value>3</value></option></acti_to_from_fk><condition		name="p_condition"><option><text>-- Condicao --</text><value /></option><option><text>Opcao 1</text><value>1</value></option><option		selected="true"><text>Opcao 2</text><value>2</value></option><option><text>Opcao 3</text><value>3</value></option></condition><event_occour		name="p_event_occour"><option><text>-- Evento --</text><value /></option><option><text>Opcao 1</text><value>1</value></option><option		selected="true"><text>Opcao 2</text><value>2</value></option><option><text>Opcao 3</text><value>3</value></option></event_occour><recbido		name="p_recbido"><option><text>-- Recebido/Enviado --</text><value /></option><option		selected="true"><text>Opcao 1</text><value>1</value></option><option><text>Opcao 2</text><value>2</value></option><option><text>Opcao 3</text><value>3</value></option></recbido><msg_tipo_occour		name="p_msg_tipo_occour"><option><text>-- Codigo/MSG --</text><value /></option><option><text>Opcao 1</text><value>1</value></option><option		selected="true"><text>Opcao 2</text><value>2</value></option><option><text>Opcao 3</text><value>3</value></option></msg_tipo_occour></list><table><destinos		type="list"><label><acti_tp_to_fk		name="p_acti_tp_to_fk"	type="text"	align="">id_tp_etapa</acti_tp_to_fk><acti_tp_to_fk_desc		name="p_acti_tp_to_fk_desc"	type="text"	align="">id_tp_etapa</acti_tp_to_fk_desc><etapa		name="p_etapa"	type="text"	align="">Etapa</etapa><etapa_desc		name="p_etapa_desc"	type="text"	align="">Etapa</etapa_desc><conditions		name="p_conditions"	type="text"	align="">Condicao</conditions><conditions_desc		name="p_conditions_desc"	type="text"	align="">Condicao</conditions_desc><destinos_id		name="p_destinos_id"	type="hidden"	align="">Condicao</destinos_id></label><value><row><acti_tp_to_fk		name="p_acti_tp_to_fk"	type="text">Leqvnqxttzmzoz</acti_tp_to_fk><acti_tp_to_fk_desc		name="p_acti_tp_to_fk_desc"	type="text">Leqvnqxttzmzoz</acti_tp_to_fk_desc><etapa		name="p_etapa"	type="text">Llzezidd</etapa><etapa_desc		name="p_etapa_desc"	type="text">Llzezidd</etapa_desc><conditions		name="p_conditions"	type="text">Ljxuvosewlcdpsddbxgm</conditions><conditions_desc		name="p_conditions_desc"	type="text">Ljxuvosewlcdpsddbxgm</conditions_desc></row><row><acti_tp_to_fk		name="p_acti_tp_to_fk"	type="text">Tnkprdgheywoop</acti_tp_to_fk><acti_tp_to_fk_desc		name="p_acti_tp_to_fk_desc"	type="text">Tnkprdgheywoop</acti_tp_to_fk_desc><etapa		name="p_etapa"	type="text">Fqxpkodes</etapa><etapa_desc		name="p_etapa_desc"	type="text">Fqxpkodes</etapa_desc><conditions		name="p_conditions"	type="text">Omxllcwrpa</conditions><conditions_desc		name="p_conditions_desc"	type="text">Omxllcwrpa</conditions_desc></row></value></destinos><events		type="list"><label><event		name="p_event"	type="text"	align="">Evento</event><event_desc		name="p_event_desc"	type="text"	align="">Evento</event_desc><acti_trans_to		name="p_acti_trans_to"	type="text"	align="">Destino</acti_trans_to><acti_trans_to_desc		name="p_acti_trans_to_desc"	type="text"	align="">Destino</acti_trans_to_desc><acti_com_to		name="p_acti_com_to"	type="text"	align="">Comunic</acti_com_to><acti_com_to_desc		name="p_acti_com_to_desc"	type="text"	align="">Comunic</acti_com_to_desc><msg_tipo		name="p_msg_tipo"	type="text"	align="">Codigo/MSG</msg_tipo><msg_tipo_desc		name="p_msg_tipo_desc"	type="text"	align="">Codigo/MSG</msg_tipo_desc><events_id		name="p_events_id"	type="hidden"	align="">Codigo/MSG</events_id></label><value><row><event		name="p_event"	type="text">Bacsqakarmujbtmmkq</event><event_desc		name="p_event_desc"	type="text">Bacsqakarmujbtmmkq</event_desc><acti_trans_to		name="p_acti_trans_to"	type="text">Ecxmcoidvowppplxhyalgpy</acti_trans_to><acti_trans_to_desc		name="p_acti_trans_to_desc"	type="text">Ecxmcoidvowppplxhyalgpy</acti_trans_to_desc><acti_com_to		name="p_acti_com_to"	type="text">Mizkv</acti_com_to><acti_com_to_desc		name="p_acti_com_to_desc"	type="text">Mizkv</acti_com_to_desc><msg_tipo		name="p_msg_tipo"	type="text">Oatmnd</msg_tipo><msg_tipo_desc		name="p_msg_tipo_desc"	type="text">Oatmnd</msg_tipo_desc></row><row><event		name="p_event"	type="text">Jgofxzqhysqztxtzpnqkwwyrw</event><event_desc		name="p_event_desc"	type="text">Jgofxzqhysqztxtzpnqkwwyrw</event_desc><acti_trans_to		name="p_acti_trans_to"	type="text">Oaktfy</acti_trans_to><acti_trans_to_desc		name="p_acti_trans_to_desc"	type="text">Oaktfy</acti_trans_to_desc><acti_com_to		name="p_acti_com_to"	type="text">Mmvabonrrmbxdvscqdjkbhgkd</acti_com_to><acti_com_to_desc		name="p_acti_com_to_desc"	type="text">Mmvabonrrmbxdvscqdjkbhgkd</acti_com_to_desc><msg_tipo		name="p_msg_tipo"	type="text">Hswgpfc</msg_tipo><msg_tipo_desc		name="p_msg_tipo_desc"	type="text">Hswgpfc</msg_tipo_desc></row></value></events></table><tools-bar><item		type="specific"><title>Start</title><app>REDGLOBAL</app><page>CONF_PROCESSO</page><link>CONF_ENGINE</link><target>submit</target><img>iniciar_processo.png</img></item><item		type="specific"><title>Next</title><app>REDGLOBAL</app><page>CONF_PROCESSO</page><link>CONF_ENGINE</link><target>submit</target><img>next.png</img></item><item		type="specific"><title>Finish</title><app>REDGLOBAL</app><page>CONF_PROCESSO</page><link>CONF_ENGINE</link><target>submit</target><img>error.png</img></item></tools-bar></form></content></rows>