<?xml version="1.0" encoding="utf-8"?><?xml-stylesheet href="../REDGLOBAL_RNIVIEW_RNI_BI_FORM_form.xsl?v={1117AFBC-447F-56B9-E050-040A84061992}" type="text/xsl"?><rows><title>IGRP</title><version>11172840AAEAF657E050040A840617F0</version><link>/images/IGRP2.2/xml/IGRP-home.xml</link><site><welcome_note>Ola</welcome_note><footer_note>2011 - Copyright NOSI</footer_note><user_name>red-igrp</user_name><button		type="specific"><title>Sair</title><app>RED</app><page /><link>#</link><target>_self</target><img>exit.png</img></button></site><app>REDGLOBAL</app><page>RNI.VIEW_RNI_BI</page><navigation	file="navigation.xml?v={1117AFBC-447E-56B9-E050-040A84061992}"	prm_app="p_prm_app"	prm_page="p_prm_page"	prm_action="p_prm_action" /><top_menu	file="/images/IGRP2.2/xml/IGRP-top_menu.xml" /><slide-menu	file="slide-menu.xml?v=31" /><language	file="/images/IGRP2.2/xml/IGRP-language.xml" /><content		type="dash"><title>Pesquisa BI</title><filter		tab=""><label><fw_db		name="p_fw_db"	type="select"	maxlength="30">Base Dados</fw_db><nome		name="p_nome"	type="text"	maxlength="100">Nome</nome><bi		name="p_bi"	type="number"	maxlength="22">BI</bi></label><value><nome		name="p_nome">Acxazvuvtedxzkjafphmqzy</nome><bi		name="p_bi">8666282</bi></value><list><fw_db		name="p_fw_db"><option><text>-- Base Dados --</text><value /></option><option><text>Opcao 1</text><value>1</value></option><option		selected="true"><text>Opcao 2</text><value>2</value></option><option><text>Opcao 3</text><value>3</value></option></fw_db></list><tools-bar><item		type="specific"><title>Pesquisar</title><app>REDGLOBAL</app><page>RNI.VIEW_RNI_BI</page><link>BULK</link><target>_self</target><img>search.png</img></item></tools-bar></filter><table		operation=""><label><bi		name="p_bi"	type="js_passa_valor"	align="center">BI</bi><nome		name="p_nome"	type="js_passa_valor"	align="left">Nome</nome><dt_nasc		name="p_dt_nasc"	type="text"	align="left">Dt. Nasc</dt_nasc><sexo		name="p_sexo"	type="text"	align="left">Sexo</sexo><nome_pai		name="p_nome_pai"	type="text"	align="left">Nome Pai</nome_pai><nome_mae		name="p_nome_mae"	type="text"	align="left">Nome Mae</nome_mae><name		name="p_name"	type="hidden"	align="left">name</name><numero		name="p_numero"	type="hidden"	align="left">numero</numero><nu_bi		name="p_nu_bi"	type="hidden"	align="left">nu_bi</nu_bi><nm_mae		name="p_nm_mae"	type="hidden"	align="left">nm_mae</nm_mae><nm_pai		name="p_nm_pai"	type="hidden"	align="left">nm_pai</nm_pai><estado_civil		name="p_estado_civil"	type="hidden"	align="left">estado_civil</estado_civil><sexo		name="p_sexo"	type="hidden"	align="left">sexo</sexo><morada		name="p_morada"	type="hidden"	align="left">morada</morada><nat_freguesia		name="p_nat_freguesia"	type="hidden"	align="left">nat_freguesia</nat_freguesia><dt_emissao		name="p_dt_emissao"	type="hidden"	align="left">dt_emissao</dt_emissao><dt_validade		name="p_dt_validade"	type="hidden"	align="left">dt_validade</dt_validade><emissor		name="p_emissor"	type="hidden"	align="left">emissor</emissor><nat_ilha		name="p_nat_ilha"	type="hidden"	align="left">nat_ilha</nat_ilha><res_ilha		name="p_res_ilha"	type="hidden"	align="left">res_ilha</res_ilha><nat_concelho		name="p_nat_concelho"	type="hidden"	align="left">nat_concelho</nat_concelho><res_concelho		name="p_res_concelho"	type="hidden"	align="left">res_concelho</res_concelho><res_freguesia		name="p_res_freguesia"	type="hidden"	align="left">res_freguesia</res_freguesia><doctype		name="p_doctype"	type="hidden"	align="left">doctype</doctype><estcivil_cad		name="p_estcivil_cad"	type="hidden"	align="left">estcivil_cad</estcivil_cad></label><value><row><bi		name="p_estcivil_cad"	type="hidden"	align="left">Tpzskel</bi><nome		name="p_estcivil_cad"	type="hidden"	align="left">Yssobmqlzvwlbvnxeqund</nome><dt_nasc		name="p_estcivil_cad"	type="hidden"	align="left">Rgykh</dt_nasc><sexo		name="p_estcivil_cad"	type="hidden"	align="left">590497</sexo><nome_pai		name="p_estcivil_cad"	type="hidden"	align="left">Qlikakd</nome_pai><nome_mae		name="p_estcivil_cad"	type="hidden"	align="left">Xmeynigefxgt</nome_mae><name		name="p_estcivil_cad"	type="hidden"	align="left">6176835</name><numero		name="p_estcivil_cad"	type="hidden"	align="left">7631077</numero><nu_bi		name="p_estcivil_cad"	type="hidden"	align="left">6460047</nu_bi><nm_mae		name="p_estcivil_cad"	type="hidden"	align="left">5713298</nm_mae><nm_pai		name="p_estcivil_cad"	type="hidden"	align="left">8037055</nm_pai><estado_civil		name="p_estcivil_cad"	type="hidden"	align="left">4394155</estado_civil><sexo		name="p_estcivil_cad"	type="hidden"	align="left">590497</sexo><morada		name="p_estcivil_cad"	type="hidden"	align="left">9947393</morada><nat_freguesia		name="p_estcivil_cad"	type="hidden"	align="left">8270612</nat_freguesia><dt_emissao		name="p_estcivil_cad"	type="hidden"	align="left">201524</dt_emissao><dt_validade		name="p_estcivil_cad"	type="hidden"	align="left">8471735</dt_validade><emissor		name="p_estcivil_cad"	type="hidden"	align="left">1335712</emissor><nat_ilha		name="p_estcivil_cad"	type="hidden"	align="left">9436337</nat_ilha><res_ilha		name="p_estcivil_cad"	type="hidden"	align="left">1522389</res_ilha><nat_concelho		name="p_estcivil_cad"	type="hidden"	align="left">1029563</nat_concelho><res_concelho		name="p_estcivil_cad"	type="hidden"	align="left">9460335</res_concelho><res_freguesia		name="p_estcivil_cad"	type="hidden"	align="left">9229043</res_freguesia><doctype		name="p_estcivil_cad"	type="hidden"	align="left">998940</doctype><estcivil_cad		name="p_estcivil_cad"	type="hidden"	align="left">7164589</estcivil_cad></row><row><bi		name="p_estcivil_cad"	type="hidden"	align="left">Jjphwjhxeeenphjgi</bi><nome		name="p_estcivil_cad"	type="hidden"	align="left">Krlvwuukvi</nome><dt_nasc		name="p_estcivil_cad"	type="hidden"	align="left">Rpohvb</dt_nasc><sexo		name="p_estcivil_cad"	type="hidden"	align="left">2080372</sexo><nome_pai		name="p_estcivil_cad"	type="hidden"	align="left">Aubhmgibnftp</nome_pai><nome_mae		name="p_estcivil_cad"	type="hidden"	align="left">Hbigdtlqjbxmmzgpnwkajtwy</nome_mae><name		name="p_estcivil_cad"	type="hidden"	align="left">3724443</name><numero		name="p_estcivil_cad"	type="hidden"	align="left">9520992</numero><nu_bi		name="p_estcivil_cad"	type="hidden"	align="left">6901228</nu_bi><nm_mae		name="p_estcivil_cad"	type="hidden"	align="left">5106128</nm_mae><nm_pai		name="p_estcivil_cad"	type="hidden"	align="left">7660257</nm_pai><estado_civil		name="p_estcivil_cad"	type="hidden"	align="left">4944262</estado_civil><sexo		name="p_estcivil_cad"	type="hidden"	align="left">2080372</sexo><morada		name="p_estcivil_cad"	type="hidden"	align="left">8092281</morada><nat_freguesia		name="p_estcivil_cad"	type="hidden"	align="left">7848323</nat_freguesia><dt_emissao		name="p_estcivil_cad"	type="hidden"	align="left">9974204</dt_emissao><dt_validade		name="p_estcivil_cad"	type="hidden"	align="left">9347727</dt_validade><emissor		name="p_estcivil_cad"	type="hidden"	align="left">8544425</emissor><nat_ilha		name="p_estcivil_cad"	type="hidden"	align="left">227264</nat_ilha><res_ilha		name="p_estcivil_cad"	type="hidden"	align="left">6234316</res_ilha><nat_concelho		name="p_estcivil_cad"	type="hidden"	align="left">3640762</nat_concelho><res_concelho		name="p_estcivil_cad"	type="hidden"	align="left">7319935</res_concelho><res_freguesia		name="p_estcivil_cad"	type="hidden"	align="left">9858281</res_freguesia><doctype		name="p_estcivil_cad"	type="hidden"	align="left">2424975</doctype><estcivil_cad		name="p_estcivil_cad"	type="hidden"	align="left">7530581</estcivil_cad></row><row><bi		name="p_estcivil_cad"	type="hidden"	align="left">Ancuemnpmmnayrh</bi><nome		name="p_estcivil_cad"	type="hidden"	align="left">Tvhybuengzbmi</nome><dt_nasc		name="p_estcivil_cad"	type="hidden"	align="left">Hkhzsxj</dt_nasc><sexo		name="p_estcivil_cad"	type="hidden"	align="left">3012299</sexo><nome_pai		name="p_estcivil_cad"	type="hidden"	align="left">Myqnrdjuczkagruhn</nome_pai><nome_mae		name="p_estcivil_cad"	type="hidden"	align="left">Gnjvzulgyipxsfuxmtx</nome_mae><name		name="p_estcivil_cad"	type="hidden"	align="left">7772245</name><numero		name="p_estcivil_cad"	type="hidden"	align="left">1554709</numero><nu_bi		name="p_estcivil_cad"	type="hidden"	align="left">1625229</nu_bi><nm_mae		name="p_estcivil_cad"	type="hidden"	align="left">9863350</nm_mae><nm_pai		name="p_estcivil_cad"	type="hidden"	align="left">2337972</nm_pai><estado_civil		name="p_estcivil_cad"	type="hidden"	align="left">2576086</estado_civil><sexo		name="p_estcivil_cad"	type="hidden"	align="left">3012299</sexo><morada		name="p_estcivil_cad"	type="hidden"	align="left">7961931</morada><nat_freguesia		name="p_estcivil_cad"	type="hidden"	align="left">366201</nat_freguesia><dt_emissao		name="p_estcivil_cad"	type="hidden"	align="left">3425548</dt_emissao><dt_validade		name="p_estcivil_cad"	type="hidden"	align="left">3898471</dt_validade><emissor		name="p_estcivil_cad"	type="hidden"	align="left">5583963</emissor><nat_ilha		name="p_estcivil_cad"	type="hidden"	align="left">9854178</nat_ilha><res_ilha		name="p_estcivil_cad"	type="hidden"	align="left">7224623</res_ilha><nat_concelho		name="p_estcivil_cad"	type="hidden"	align="left">8699877</nat_concelho><res_concelho		name="p_estcivil_cad"	type="hidden"	align="left">3691842</res_concelho><res_freguesia		name="p_estcivil_cad"	type="hidden"	align="left">3041120</res_freguesia><doctype		name="p_estcivil_cad"	type="hidden"	align="left">8995412</doctype><estcivil_cad		name="p_estcivil_cad"	type="hidden"	align="left">9560022</estcivil_cad></row><row><bi		name="p_estcivil_cad"	type="hidden"	align="left">Ovhaba</bi><nome		name="p_estcivil_cad"	type="hidden"	align="left">Xwuegcpmpudzxro</nome><dt_nasc		name="p_estcivil_cad"	type="hidden"	align="left">Fkbimm</dt_nasc><sexo		name="p_estcivil_cad"	type="hidden"	align="left">4772932</sexo><nome_pai		name="p_estcivil_cad"	type="hidden"	align="left">Hayqiewihuvehgstosqhjmj</nome_pai><nome_mae		name="p_estcivil_cad"	type="hidden"	align="left">Xqnodvkevdwkujybx</nome_mae><name		name="p_estcivil_cad"	type="hidden"	align="left">3973307</name><numero		name="p_estcivil_cad"	type="hidden"	align="left">315767</numero><nu_bi		name="p_estcivil_cad"	type="hidden"	align="left">9841580</nu_bi><nm_mae		name="p_estcivil_cad"	type="hidden"	align="left">9043275</nm_mae><nm_pai		name="p_estcivil_cad"	type="hidden"	align="left">6469627</nm_pai><estado_civil		name="p_estcivil_cad"	type="hidden"	align="left">9746076</estado_civil><sexo		name="p_estcivil_cad"	type="hidden"	align="left">4772932</sexo><morada		name="p_estcivil_cad"	type="hidden"	align="left">8804997</morada><nat_freguesia		name="p_estcivil_cad"	type="hidden"	align="left">9892549</nat_freguesia><dt_emissao		name="p_estcivil_cad"	type="hidden"	align="left">3933695</dt_emissao><dt_validade		name="p_estcivil_cad"	type="hidden"	align="left">4229533</dt_validade><emissor		name="p_estcivil_cad"	type="hidden"	align="left">3010455</emissor><nat_ilha		name="p_estcivil_cad"	type="hidden"	align="left">6685124</nat_ilha><res_ilha		name="p_estcivil_cad"	type="hidden"	align="left">2217417</res_ilha><nat_concelho		name="p_estcivil_cad"	type="hidden"	align="left">947035</nat_concelho><res_concelho		name="p_estcivil_cad"	type="hidden"	align="left">8310555</res_concelho><res_freguesia		name="p_estcivil_cad"	type="hidden"	align="left">7395263</res_freguesia><doctype		name="p_estcivil_cad"	type="hidden"	align="left">6014934</doctype><estcivil_cad		name="p_estcivil_cad"	type="hidden"	align="left">2273442</estcivil_cad></row><row><bi		name="p_estcivil_cad"	type="hidden"	align="left">Gncxsobqrumms</bi><nome		name="p_estcivil_cad"	type="hidden"	align="left">Euixqpiktevjmpbwuqme</nome><dt_nasc		name="p_estcivil_cad"	type="hidden"	align="left">Mqblztl</dt_nasc><sexo		name="p_estcivil_cad"	type="hidden"	align="left">5545124</sexo><nome_pai		name="p_estcivil_cad"	type="hidden"	align="left">Ajrjv</nome_pai><nome_mae		name="p_estcivil_cad"	type="hidden"	align="left">Uqeecwontlwgezhzihpt</nome_mae><name		name="p_estcivil_cad"	type="hidden"	align="left">423402</name><numero		name="p_estcivil_cad"	type="hidden"	align="left">6720767</numero><nu_bi		name="p_estcivil_cad"	type="hidden"	align="left">9559746</nu_bi><nm_mae		name="p_estcivil_cad"	type="hidden"	align="left">1432950</nm_mae><nm_pai		name="p_estcivil_cad"	type="hidden"	align="left">6805806</nm_pai><estado_civil		name="p_estcivil_cad"	type="hidden"	align="left">2110716</estado_civil><sexo		name="p_estcivil_cad"	type="hidden"	align="left">5545124</sexo><morada		name="p_estcivil_cad"	type="hidden"	align="left">4137192</morada><nat_freguesia		name="p_estcivil_cad"	type="hidden"	align="left">5956346</nat_freguesia><dt_emissao		name="p_estcivil_cad"	type="hidden"	align="left">1023431</dt_emissao><dt_validade		name="p_estcivil_cad"	type="hidden"	align="left">3707756</dt_validade><emissor		name="p_estcivil_cad"	type="hidden"	align="left">7006432</emissor><nat_ilha		name="p_estcivil_cad"	type="hidden"	align="left">3460163</nat_ilha><res_ilha		name="p_estcivil_cad"	type="hidden"	align="left">285990</res_ilha><nat_concelho		name="p_estcivil_cad"	type="hidden"	align="left">4878472</nat_concelho><res_concelho		name="p_estcivil_cad"	type="hidden"	align="left">8631409</res_concelho><res_freguesia		name="p_estcivil_cad"	type="hidden"	align="left">1778679</res_freguesia><doctype		name="p_estcivil_cad"	type="hidden"	align="left">8684890</doctype><estcivil_cad		name="p_estcivil_cad"	type="hidden"	align="left">6658665</estcivil_cad></row></value></table></content></rows>