<?xml version="1.0" encoding="utf-8"?><?xml-stylesheet href="../REDGLOBAL_CONF_PROCESSO_INPUTS_table.xsl?v={10DDEDAC-8FFD-A81B-E050-040A840656C3}" type="text/xsl"?><rows><title>IGRP</title><version>201510</version><link>/images/IGRP2.2/xml/IGRP-home.xml</link><site><welcome_note>Ola</welcome_note><footer_note>2011 - Copyright NOSI</footer_note><user_name>red-igrp</user_name><button		type="specific"><title>Sair</title><app /><page /><link>#</link><target>_self</target><img>exit.png</img></button></site><app>REDGLOBAL</app><page>CONF_PROCESSO</page><navigation	file="navigation.xml?v={10DDEDAC-8FFB-A81B-E050-040A840656C3}"	prm_app="p_prm_app"	prm_page="p_prm_page"	prm_action="p_prm_action" /><top_menu	file="/images/IGRP2.2/xml/IGRP-top_menu.xml" /><slide-menu	file="slide-menu.xml?v=5" /><language	file="/images/IGRP2.2/xml/IGRP-language.xml" /><content		type="table"><title>Documentos Inputs</title><form		tab=""><label><acti_tp_fk		name="p_acti_tp_fk"	type="hidden"	maxlength="30">acti_tp_fk</acti_tp_fk><direction		name="p_direction"	type="hidden"	maxlength="30">direction</direction><proc_tp_fk		name="p_proc_tp_fk"	type="hidden"	maxlength="30">proc_tp_fk</proc_tp_fk></label><value><hidden		name="p_acti_tp_fk">7738455</hidden><hidden		name="p_direction">1248440</hidden><hidden		name="p_proc_tp_fk">874372</hidden></value><tools-bar><item		type="specific"><title>Pesquisar</title><app>REDGLOBAL</app><page>CONF_PROCESSO</page><link>INPUTS</link><target>_self</target><img>search.png</img></item></tools-bar></form><table		operation=""><label><doc_tp_fk		name="p_doc_tp_fk"	type="checkbox"	align="center">Tipo Documento</doc_tp_fk><doc_tp_fk_check		name="p_doc_tp_fk_check"	type="field_copy"	align="center">Tipo Documento</doc_tp_fk_check><doc_tp_fk_desc		name="p_doc_tp_fk_desc"	type="field_copy"	align="center">Tipo Documento</doc_tp_fk_desc><documento		name="p_documento"	type="text"	align="left">Documento</documento></label><value><row><doc_tp_fk	name="p_documento"	type="text"	align="left" /><doc_tp_fk_check	name="p_documento"	type="text"	align="left" /><doc_tp_fk_desc	name="p_documento"	type="text"	align="left" /><documento		name="p_documento"	type="text"	align="left">Gqpuoaf</documento></row><row><doc_tp_fk	name="p_documento"	type="text"	align="left" /><doc_tp_fk_check	name="p_documento"	type="text"	align="left" /><doc_tp_fk_desc	name="p_documento"	type="text"	align="left" /><documento		name="p_documento"	type="text"	align="left">Vlxfjzkiwyoze</documento></row><row><doc_tp_fk	name="p_documento"	type="text"	align="left" /><doc_tp_fk_check	name="p_documento"	type="text"	align="left" /><doc_tp_fk_desc	name="p_documento"	type="text"	align="left" /><documento		name="p_documento"	type="text"	align="left">Alvjjmvk</documento></row><row><doc_tp_fk	name="p_documento"	type="text"	align="left" /><doc_tp_fk_check	name="p_documento"	type="text"	align="left" /><doc_tp_fk_desc	name="p_documento"	type="text"	align="left" /><documento		name="p_documento"	type="text"	align="left">Fzjacyindzekuhdmlnebirg</documento></row><row><doc_tp_fk	name="p_documento"	type="text"	align="left" /><doc_tp_fk_check	name="p_documento"	type="text"	align="left" /><doc_tp_fk_desc	name="p_documento"	type="text"	align="left" /><documento		name="p_documento"	type="text"	align="left">Cazgkkrxuuyih</documento></row></value><tools-bar><item		type="specific"><title>Gravar</title><app>REDGLOBAL</app><page>CONF_PROCESSO</page><link>INPUTS</link><target>submit</target><img>save.png</img></item><item		type="specific"><title>Fechar</title><app>REDGLOBAL</app><page>REDWF.GLB_T_ACTIVITY_TYPE</page><link>BULK</link><target>_close</target><img>ctx-close.png</img></item></tools-bar></table></content></rows>