<?xml version="1.0" encoding="UTF-8"?>
<?xml-stylesheet href="../SA_MA_MA_table.xsl" type="text/xsl"?>
<rows>
    <site>
        <welcome_note>Ola</welcome_note>
        <footer_note>2011 - Copyright NOSI</footer_note>
        <user_name>red-igrp</user_name>
        <button type="specific">
            <title>Sair</title>
            <app>RED</app>
            <page />
            <link>#</link>
            <target>_self</target>
            <img>exit.png</img>
        </button>
    </site>
    <page>MA</page>
    <app>SA</app>
    <plsql>
        <action>MA</action>
        <package_instance></package_instance>
        <package_db>SA_MARCA_LISTA_NOVO_DB</package_db>
        <package_html>SA_MARCA_LISTA_NOVO_HTML</package_html>
        <table_name></table_name>
        <with_replace>true</with_replace>
        <with_label>true</with_label>
        <with_biztalk>false</with_biztalk>
        <dynamic_menu>false</dynamic_menu>
        <copy_menu>false</copy_menu>
        <package_copy_db />
        <package_copy_html />
        <preserve_url>https://nosiappsdev.gov.cv/redglobal_dev/red.form_designer_db.preserve_your_code</preserve_url>
    </plsql>
    <content>
        <title>LISTA NOVO</title>
        <page_title type="sectionheader" xml-type="form" gen-type="container" gen-group="">
            <fields>
                <page_title_text type="text" name="p_page_title_text" persist="true" maxlength="100">
                    <value>
                        <![CDATA[Gestão de Marca ]]>
                    </value>
                </page_title_text>
            </fields>
        </page_title>
        <form_filtro type="form" xml-type="form" gen-type="container" gen-group="">
            <fields>
                <nome name="p_nome" type="text" required="false" change="false" readonly="false" disabled="false" maxlength="300" right="false" placeholder="">
                    <label>Nome</label>
                    <value>Accusantium ut dolor aliqua laudantium</value>
                </nome>
                <descricao name="p_descricao" type="text" required="false" change="false" readonly="false" disabled="false" maxlength="300" right="false" placeholder="">
                    <label>Descrição</label>
                    <value>Totam adipiscing stract amet natus</value>
                </descricao>
            </fields>
            <tools-bar>
                <item type="form" code="" class="success" rel="novo">
                    <title>Novo</title>
                    <app>SA</app>
                    <page>MA</page>
                    <link>MAF</link>
                    <target>modal</target>
                    <img>success|fa-plus</img>
                </item>
                <item type="form" code="" class="info" rel="pesquisar">
                    <title>Pesquisar</title>
                    <app>SA</app>
                    <page>MA</page>
                    <link>MA</link>
                    <target>submit</target>
                    <img>info|fa-search</img>
                </item>
            </tools-bar>
        </form_filtro>
        <gen_table type="table" xml-type="table" gen-type="container" gen-group="true">
            <fields>
                <nome_list name="p_nome_list" type="text" align="left" maxlength="300" lookup_parser="false">
                    <label>Nome</label>
                </nome_list>
                <descricao_list name="p_descricao_list" type="text" align="left" maxlength="300" lookup_parser="false">
                    <label>Descrição</label>
                </descricao_list>
                <id name="p_id" type="hidden" maxlength="30" tag="id"/>
            </fields>
            <table>
                <value>
                    <row>
                        <context-menu>
                            <param>p1=linha1</param>
                            <param>p2=linha1</param>
                        </context-menu>
                        <nome_list name="p_nome_list">Dolor rem consectetur sit stract</nome_list>
                        <descricao_list name="p_descricao_list">Deserunt amet natus laudantium mollit</descricao_list>
                        <id name="p_id" tag="id">1</id>
                    </row>
                    <row>
                        <context-menu>
                            <param>p1=linha1</param>
                            <param>p2=linha1</param>
                        </context-menu>
                        <nome_list name="p_nome_list">Anim labore adipiscing stract deserunt</nome_list>
                        <descricao_list name="p_descricao_list">Doloremque sed adipiscing officia ut</descricao_list>
                        <id name="p_id" tag="id">1</id>
                    </row>
                    <row>
                        <context-menu>
                            <param>p1=linha1</param>
                            <param>p2=linha1</param>
                        </context-menu>
                        <nome_list name="p_nome_list">Stract rem labore unde deserunt</nome_list>
                        <descricao_list name="p_descricao_list">Amet labore magna dolor ipsum</descricao_list>
                        <id name="p_id" tag="id">1</id>
                    </row>
                    <row>
                        <context-menu>
                            <param>p1=linha1</param>
                            <param>p2=linha1</param>
                        </context-menu>
                        <nome_list name="p_nome_list">Elit unde ipsum omnis magna</nome_list>
                        <descricao_list name="p_descricao_list">Doloremque deserunt ut officia laudantium</descricao_list>
                        <id name="p_id" tag="id">1</id>
                    </row>
                </value>
                <context-menu>
                    <item type="specific" code="" class="warning" rel="editar">
                        <title>Editar</title>
                        <app>SA</app>
                        <page>MA</page>
                        <link>MAF</link>
                        <target>modal</target>
                        <img>warning|fa-edit</img>
                    </item>
                    <item type="specific" code="" class="danger" rel="eliminar">
                        <title>Eliminar</title>
                        <app>SA</app>
                        <page>MA</page>
                        <link>MA</link>
                        <target>alert_submit</target>
                        <img>danger|fa-minus-circle</img>
                    </item>
                </context-menu>
            </table>
        </gen_table>
    </content>
</rows>