<?xml version="1.0" encoding="utf-8"?><?xml-stylesheet href="../SA_SASA_T_MARCA_FORM_form.xsl?v={482F749C-CE22-D41B-E050-040A080266BF}" type="text/xsl"?><rows><title>Sistema Atendimento</title><version>482F6F02AE8E790DE050040A08026669</version><template>c_cidadao</template><link>/IGRP//IGRP2.3xml/IGRP-home.xml</link><head_version>IGRP2.3</head_version><site><welcome_note>Ola</welcome_note><footer_note>2011 - Copyright NOSI</footer_note><user_name>red-igrp</user_name><button		type="specific"	code=""><title>Sair</title><app>SA</app><page /><link>#</link><target>_self</target><img>exit.png</img></button></site><app>SA</app><page>SA.SA_T_MARCA</page><plsql><action>BULK</action><package_db>SA_MARCA_DB</package_db><package_html>SA_MARCA_HTML</package_html><package_instance /><table_name>SA.SA_T_MARCA</table_name><with_replace>false</with_replace><with_label>false</with_label><with_biztalk>false</with_biztalk><dynamic_menu>false</dynamic_menu><copy_menu>false</copy_menu><package_copy_db /><package_copy_html /></plsql><navigation	file="navigation.xml?v={482F749C-CE21-D41B-E050-040A080266BF}"	prm_app="p_prm_app"	prm_page="p_prm_page"	prm_action="p_prm_action" /><top_menu	file="/IGRP//IGRP2.3xml/IGRP-top_menu.xml" /><slide-menu	file="slide-menu.xml?v=8" /><content		type="form"><title>sa.sa_t_marca</title><form		tab=""><label><id_marca		name="p_id_marca"	type="hidden"	required="true"	maxlength="22"	code="ID_MARCA">Id_Marca</id_marca><nome		name="p_nome"	type="text"	required="true"	maxlength="20"	code="NOME">Nome</nome><descricao		name="p_descricao"	type="text"	maxlength="20"	code="DESCRICAO">Descricao</descricao><modelo		type="separatorlist"	container="true"	code="MODELO">Modelo</modelo><mnome		name="p_mnome"	type="text"	required="true"	rel="modelo"	maxlength="100"	code="MNOME">Nome</mnome><mdescricao		name="p_mdescricao"	type="text"	rel="modelo"	maxlength="200"	code="MDESCRICAO">Descricao</mdescricao></label><value><nome		name="p_nome">Eyyizffdnpgbhaaultk</nome><descricao		name="p_descricao">Hbrqxp</descricao><mnome		name="p_mnome">Hdmwwwpbtcaophyibdlh</mnome><mdescricao		name="p_mdescricao">Dnfyipcnmo</mdescricao><hidden		name="p_id_marca">8176463</hidden></value><table><modelo		type="separatorlist"	container="true"><label><mnome		name="p_mnome"	type="text"	align="">Nome</mnome><mnome_desc		name="p_mnome_desc"	type="text"	align="">Nome</mnome_desc><mdescricao		name="p_mdescricao"	type="text"	align="">Descricao</mdescricao><mdescricao_desc		name="p_mdescricao_desc"	type="text"	align="">Descricao</mdescricao_desc><modelo_id		name="p_modelo_id"	type="hidden"	align="">Descricao</modelo_id></label><value><row><mnome		name="p_mnome"	type="text">Smswttaahjerxfpsmgukmmbhk</mnome><mnome_desc		name="p_mnome_desc"	type="text">Smswttaahjerxfpsmgukmmbhk</mnome_desc><mdescricao		name="p_mdescricao"	type="text">Gxwsshyiqtqyelfrkrtkvf</mdescricao><mdescricao_desc		name="p_mdescricao_desc"	type="text">Gxwsshyiqtqyelfrkrtkvf</mdescricao_desc></row><row><mnome		name="p_mnome"	type="text">Zrxaiydxyuq</mnome><mnome_desc		name="p_mnome_desc"	type="text">Zrxaiydxyuq</mnome_desc><mdescricao		name="p_mdescricao"	type="text">Tigrvlneuerxebfwwnxjyvx</mdescricao><mdescricao_desc		name="p_mdescricao_desc"	type="text">Tigrvlneuerxebfwwnxjyvx</mdescricao_desc></row></value></modelo></table><tools-bar><item		type="specific"	code="FORM_GRAVAR"><title>Gravar</title><app>SA</app><page>SA.SA_T_MARCA</page><link>FORM</link><target>submit</target><img>save.png</img></item><item		type="specific"	code="FORM_VOLTAR"><title>Voltar</title><app>SA</app><page>SA.SA_T_MARCA</page><link>BULK</link><target>_self</target><img>back.png</img></item></tools-bar></form></content></rows>