<?xml version="1.0" encoding="UTF-8"?>
<?xml-stylesheet href="/IGRP/images/IGRP/IGRP2.3/app/igrp_studio/partilha_geral/Partilha_geral.xsl" type="text/xsl"?>
<rows>
    <link_img>/IGRP/images/IGRP/IGRP2.3</link_img>
    <site>
        <welcome_note>Oba</welcome_note>
        <footer_note>2017 - Copyright NOSI</footer_note>
        <user_name>Hexagon</user_name>
        <button type="specific">
            <title>Sair</title>
            <app>DUA</app>
            <page />
            <link>#</link>
            <target>_self</target>
            <img>exit.png</img>
        </button>
    </site>
    <page>Partilha_geral</page>
    <app>igrp_studio</app>
    <plsql>
        <action>index</action>
        <package_instance></package_instance>
        <package_db>nosi.webapps.igrp_studio.pages</package_db>
        <package_html>Partilha_geral</package_html>
        <table_name></table_name>
        <with_replace>false</with_replace>
        <with_label>false</with_label>
        <with_biztalk>false</with_biztalk>
        <dynamic_menu>false</dynamic_menu>
        <copy_menu>false</copy_menu>
        <package_copy_db />
        <package_copy_html />
        <preserve_url>webapps?r=igrp/page/preserveUrl&amp;p_id=49</preserve_url>
    </plsql>
    <content>
        <title>Partilha Geral</title>
        <sectionheader_1 type="sectionheader" xml-type="form" gen-type="container" gen-group="">
            <fields>
                <sectionheader_1_text type="text" name="p_sectionheader_1_text" persist="true" maxlength="4000">
                    <value>Partilha Geral - Inter Aplicações (Páginas)</value>
                </sectionheader_1_text>
            </fields>
        </sectionheader_1>
        <toolsbar_1 type="toolsbar" xml-type="toolsbar" gen-type="menu" gen-group="">
            <item type="specific" code="" rel="partilhar">
                <title>Partilhar</title>
                <app>igrp_studio</app>
                <page>Partilha_geral</page>
                <link>index</link>
                <target>submit</target>
                <img>success|fa-share-alt</img>
                <preview>/IGRP/images/IGRP/IGRP2.3/app/igrp_studio/partilha_geral/Partilha_geral.xml</preview>
            </item>
        </toolsbar_1>
        <form_1 type="form" xml-type="form" gen-type="container" gen-group="">
            <fields>
                <aplicacao_origem name="p_aplicacao_origem" type="select" multiple="false" domain="" maxlength="50" required="true" change="true" disabled="false" right="false" java-type="">
                    <label>Aplicação Origem</label>
                    <list>
                        <option/>
                        <option>
                            <text>Option 1</text>
                            <value>1</value>
                        </option>
                        <option>
                            <text>Option 2</text>
                            <value>2</value>
                        </option>
                        <option>
                            <text>Option 3</text>
                            <value>3</value>
                        </option>
                        <option>
                            <text>Option 4</text>
                            <value>4</value>
                        </option>
                    </list>
                </aplicacao_origem>
                <elemento name="p_elemento" type="select" multiple="false" domain="" maxlength="30" required="true" change="true" disabled="false" right="false" java-type="">
                    <label>Elemento</label>
                    <list>
                        <option/>
                        <option>
                            <text>Option 1</text>
                            <value>1</value>
                        </option>
                        <option>
                            <text>Option 2</text>
                            <value>2</value>
                        </option>
                        <option>
                            <text>Option 3</text>
                            <value>3</value>
                        </option>
                        <option>
                            <text>Option 4</text>
                            <value>4</value>
                        </option>
                    </list>
                </elemento>
                <aplicacao_destino name="p_aplicacao_destino" type="select" multiple="false" domain="" maxlength="50" required="true" change="true" disabled="false" right="false" java-type="">
                    <label>Aplicação Destino</label>
                    <list>
                        <option/>
                        <option>
                            <text>Option 1</text>
                            <value>1</value>
                        </option>
                        <option>
                            <text>Option 2</text>
                            <value>2</value>
                        </option>
                        <option>
                            <text>Option 3</text>
                            <value>3</value>
                        </option>
                        <option>
                            <text>Option 4</text>
                            <value>4</value>
                        </option>
                    </list>
                </aplicacao_destino>
            </fields>
        </form_1>
        <table_1 type="table" xml-type="table" gen-type="container" gen-group="true">
            <fields>
                <estado name="p_estado" type="checkbox" maxlength="30" align="left" lookup_parser="false" iskey="false" switch="false" check="true" desc="true">
                    <label>Estado</label>
                </estado>
                <descricao name="p_descricao" type="text" maxlength="100" align="left" lookup_parser="false" iskey="false">
                    <label>Descrição</label>
                </descricao>
                <hidden_1 name="p_hidden_1" type="hidden" maxlength="30" iskey="true" tag="hidden_1"/>
            </fields>
            <table>
                <value>
                    <row>
                        <estado name="p_estado" check="true" desc="true">1</estado>
                        <estado_desc name="p_estado_desc">1</estado_desc>
                        <descricao name="p_descricao">Consectetur ipsum voluptatem mollit lorem</descricao>
                        <hidden_1 name="p_hidden_1" tag="hidden_1">1</hidden_1>
                    </row>
                    <row>
                        <estado name="p_estado" check="true" desc="true">1</estado>
                        <estado_desc name="p_estado_desc">1</estado_desc>
                        <descricao name="p_descricao">Amet natus ut labore natus</descricao>
                        <hidden_1 name="p_hidden_1" tag="hidden_1">1</hidden_1>
                    </row>
                    <row>
                        <estado name="p_estado" check="true" desc="true">1</estado>
                        <estado_desc name="p_estado_desc">1</estado_desc>
                        <descricao name="p_descricao">Elit anim stract sit ipsum</descricao>
                        <hidden_1 name="p_hidden_1" tag="hidden_1">1</hidden_1>
                    </row>
                    <row>
                        <estado name="p_estado" check="true" desc="true">1</estado>
                        <estado_desc name="p_estado_desc">1</estado_desc>
                        <descricao name="p_descricao">Natus omnis adipiscing ut sit</descricao>
                        <hidden_1 name="p_hidden_1" tag="hidden_1">1</hidden_1>
                    </row>
                    <row>
                        <estado name="p_estado" check="true" desc="true">1</estado>
                        <estado_desc name="p_estado_desc">1</estado_desc>
                        <descricao name="p_descricao">Laudantium totam ipsum sit consectetur</descricao>
                        <hidden_1 name="p_hidden_1" tag="hidden_1">1</hidden_1>
                    </row>
                </value>
            </table>
        </table_1>
    </content>
</rows>
