<?xml version="1.0" encoding="utf-8"?><?xml-stylesheet href="../C_CIDADAO_TESTE_CRISTINA_BULK_dash.xsl?v=3" type="text/xsl"?><rows><title>IGRP - TESTE</title><link>/images/IGRP/xml/IGRP-home.xml</link><site><welcome_note>Ola</welcome_note><footer_note>2011 - Copyright NOSI</footer_note><user_name>red-igrp</user_name><button		type="specific"><title>Sair</title><app>RED</app><page /><link>#</link><target>_self</target><img>exit.png</img></button></site><app>C_CIDADAO</app><page>TESTE_CRISTINA</page><navigation	file="navigation.xml?v=3"	prm_app="p_prm_app"	prm_page="p_prm_page"	prm_action="p_prm_action" /><top_menu	file="/images/IGRP/xml/IGRP-top_menu.xml" /><slide-menu	file="slide-menu.xml?v=3" /><content><title>TESTE_CRISTINA</title><messages><message		type="confirm">Deseja continuar a Accao?</message></messages><menu><group		title="menu 1"><item		type="specific"><title>sub_menu 1</title><app>C_CIDADAO</app><page>VID_T_SOCIOS</page><link>A</link><target>_self</target><img>m_lista.png</img></item><item		type="specific"><title>sub_menu 1</title><app>C_CIDADAO</app><page>VID_T_FILMES</page><link>ESTAT_ALUG</link><target>_self</target><img>estatistica-financeira.png</img></item></group><group		title="menu 2"><item		type="specific"><title>sub_menu 2</title><app>C_CIDADAO</app><page>VID_T_FILMES</page><link>F</link><target>_self</target><img>estatistica_contratos.png</img></item></group></menu><filter><label><id>Id</id><nome>Nome</nome><nr_bi>Numero BI</nr_bi><nr_nif>Numero Nif</nr_nif><data_nasc>Data Nascimento</data_nasc><email>Email</email><morada>Morada</morada></label><value><id		name="p_id">768587</id><nome		name="p_nome">Xyedgkbzip</nome><nr_bi		name="p_nr_bi">4982312</nr_bi><nr_nif		name="p_nr_nif">1768775</nr_nif><data_nasc		name="p_data_nasc">25-10-2006</data_nasc><email		name="p_email">vudohtibpgfwtdt@hasmu.sl</email><morada		name="p_morada">Hfqjcjdyd</morada></value><lookup><morada>XXX</morada></lookup><tools-bar><item		type="specific"><title>Pesquisar</title><app>RED</app><page>TESTE_CRISTINA</page><link>BULK</link><target>_self</target><img>search.png</img></item></tools-bar></filter><form><label><id>Id</id><nome_pai>Nome_Pai</nome_pai><nome_mae>Nome_Mae</nome_mae><sexo>Sexo</sexo><nr_bi>Nr_Bi</nr_bi><nr_nif>Nr_Nif</nr_nif><data_nasc>Data_Nasc</data_nasc><email>Email</email><morada>Morada</morada><nome>Nome</nome></label><value><nome_pai		name="p_nome_pai">Zwmankzmlnx</nome_pai><nome_mae		name="p_nome_mae">Ieeetkww</nome_mae><nr_bi		name="p_nr_bi">8283691</nr_bi><nr_nif		name="p_nr_nif">6157574</nr_nif><data_nasc		name="p_data_nasc">21-03-2008</data_nasc><email		name="p_email">pcjpeepdukjfycd@jorle.jk</email><morada		name="p_morada">Eqxgdgstopuccq</morada><nome		name="p_nome">Hyocquzqyiljoaqlofa</nome><hidden		name="p_id">6957046</hidden></value><list><sexo		name="p_sexo"><option><text>-- Sexo --</text><value /></option><option><text>Opcao 1</text><value>1</value></option><option><text>Opcao 2</text><value>2</value></option><option><text>Opcao 3</text><value>3</value></option></sexo></list><tools-bar><item		type="specific"><title>Gravar</title><app>C_CIDADAO</app><page>TESTE_CRISTINA</page><link>FORM</link><target>submit</target><img>save.png</img></item><item		type="specific"><title>Voltar</title><app>C_CIDADAO</app><page>TESTE_CRISTINA</page><link>BULK</link><target>_self</target><img>back.png</img></item></tools-bar></form><table><label><id>Id</id><id_check>Id</id_check><id_desc>Id</id_desc><nome>Nome</nome><nome_pai>Nome Pai</nome_pai><nome_mae>Nome Mae</nome_mae><sexo>Sexo</sexo><nr_bi>Numero_Bi</nr_bi><nr_nif>Numero_Nif</nr_nif><data_nasc>Data Nascimento</data_nasc><email>Email</email><morada>Morada</morada></label><value><row><id /><id_check /><id_desc /><nome>Slwjrjemhpalicubz</nome><nome_pai>Aenchvdxditpkvn</nome_pai><nome_mae>Hzitpykz</nome_mae><sexo>Glglo</sexo><nr_bi>1729383</nr_bi><nr_nif>3319067</nr_nif><data_nasc>25-01-2008</data_nasc><email>hhlwiarlzpivdhk@qwkzj.ib</email><morada>Ziskmosjbxwswoy</morada></row><row><id /><id_check /><id_desc /><nome>Hjytnhlwirkyrtz</nome><nome_pai>Qavjx</nome_pai><nome_mae>Amwmasrfvy</nome_mae><sexo>Itxpn</sexo><nr_bi>1320922</nr_bi><nr_nif>6365685</nr_nif><data_nasc>23-06-2009</data_nasc><email>ieiskrxrcuhzxdv@ymenh.un</email><morada>Evhhghqdeoflletecmy</morada></row><row><id /><id_check /><id_desc /><nome>Sbbhfbdubuzhe</nome><nome_pai>Pysibwqa</nome_pai><nome_mae>Kbxzbydszwphjxkbh</nome_mae><sexo>Qliauk</sexo><nr_bi>5767328</nr_bi><nr_nif>7509961</nr_nif><data_nasc>14-04-2010</data_nasc><email>tmrptzbjeevuxkg@rbwrg.vy</email><morada>Eqvcooszuluhtvqq</morada></row><row><id /><id_check /><id_desc /><nome>Cfvfnxcjwlqzlhej</nome><nome_pai>Ueirbdq</nome_pai><nome_mae>Cntaxfdcmmiwoongtoa</nome_mae><sexo>Eetolb</sexo><nr_bi>7601567</nr_bi><nr_nif>3351833</nr_nif><data_nasc>12-01-2007</data_nasc><email>bijznuinzydhiws@wonsj.rf</email><morada>Kooohsrkfkwmwq</morada></row><row><id /><id_check /><id_desc /><nome>Cmfxvivxaic</nome><nome_pai>Kewcpq</nome_pai><nome_mae>Xhfmttjupdy</nome_mae><sexo>Uiukor</sexo><nr_bi>2510273</nr_bi><nr_nif>5478946</nr_nif><data_nasc>12-09-2011</data_nasc><email>qszmotzvittbcqv@wamzh.ps</email><morada>Dnscrzkigqwtugs</morada></row></value><tools-bar><item		type="specific"><title>Novo</title><app>C_CIDADAO</app><page>TESTE_CRISTINA</page><link>FORM</link><target>_self</target><img>add.png</img></item></tools-bar><context-menu><item		type="specific"><title>Editar</title><app>C_CIDADAO</app><page>TESTE_CRISTINA</page><link>FORM</link><target>_self</target><img>edit.png</img></item><item		type="specific"><title>Eliminar</title><app>C_CIDADAO</app><page>TESTE_CRISTINA</page><link>BULK</link><target>confirm</target><img>delete.png</img></item></context-menu></table></content></rows>